musiclist_for_soundiiz/__init__.py
musiclist_for_soundiiz/cli.py
musiclist_for_soundiiz/duplicate_detector.py
musiclist_for_soundiiz/exporter.py
musiclist_for_soundiiz/extractor.py
musiclist_for_soundiiz/gui.py
musiclist_for_soundiiz/i18n.py
musiclist_for_soundiiz-1.0.8.dist-info/licenses/LICENSE
musiclist_for_soundiiz-1.0.8.dist-info/METADATA
musiclist_for_soundiiz-1.0.8.dist-info/WHEEL
musiclist_for_soundiiz-1.0.8.dist-info/entry_points.txt
musiclist_for_soundiiz-1.0.8.dist-info/top_level.txt
musiclist_for_soundiiz-1.0.8.dist-info/RECORD
