Metadata-Version: 2.4
Name: musiclist-for-soundiiz
Version: 1.0.8
Summary: Extract music file metadata for Soundiiz import
Home-page: https://github.com/lucmuss/musiclist-for-soundiiz
Author: Luc Muss
Author-email: Luc Muss <lucmuss@users.noreply.github.com>
Maintainer-email: Luc Muss <lucmuss@users.noreply.github.com>
License: MIT
Project-URL: Homepage, https://github.com/lucmuss/musiclist-for-soundiiz
Project-URL: Documentation, https://github.com/lucmuss/musiclist-for-soundiiz#readme
Project-URL: Repository, https://github.com/lucmuss/musiclist-for-soundiiz
Project-URL: Issues, https://github.com/lucmuss/musiclist-for-soundiiz/issues
Project-URL: Changelog, https://github.com/lucmuss/musiclist-for-soundiiz/releases
Keywords: soundiiz,music,metadata,audio,playlist,csv,export,mp3,flac,ogg
Classifier: Development Status :: 5 - Production/Stable
Classifier: Intended Audience :: End Users/Desktop
Classifier: Topic :: Multimedia :: Sound/Audio
Classifier: Topic :: Multimedia :: Sound/Audio :: Conversion
Classifier: License :: OSI Approved :: MIT License
Classifier: Programming Language :: Python :: 3
Classifier: Programming Language :: Python :: 3.8
Classifier: Programming Language :: Python :: 3.9
Classifier: Programming Language :: Python :: 3.10
Classifier: Programming Language :: Python :: 3.11
Classifier: Programming Language :: Python :: 3.12
Classifier: Operating System :: OS Independent
Classifier: Operating System :: POSIX :: Linux
Classifier: Operating System :: Microsoft :: Windows
Classifier: Operating System :: MacOS
Classifier: Environment :: Console
Classifier: Environment :: X11 Applications
Requires-Python: >=3.8
License-File: LICENSE
Requires-Dist: mutagen>=1.45.0
Provides-Extra: dev
Requires-Dist: pytest>=7.0.0; extra == "dev"
Requires-Dist: pytest-cov>=4.0.0; extra == "dev"
Requires-Dist: black>=22.0.0; extra == "dev"
Requires-Dist: flake8>=5.0.0; extra == "dev"
Requires-Dist: isort>=5.10.0; extra == "dev"
Requires-Dist: mypy>=0.990; extra == "dev"
Requires-Dist: build>=0.10.0; extra == "dev"
Requires-Dist: twine>=4.0.0; extra == "dev"
Dynamic: author
Dynamic: home-page
Dynamic: license-file
Dynamic: requires-python
